MANIFEST.in
README.rst
setup.py
docs/HISTORY.txt
docs/INSTALL.txt
docs/LICENSE.GPL
docs/LICENSE.txt
ftw/__init__.py
ftw.journal.egg-info/PKG-INFO
ftw.journal.egg-info/SOURCES.txt
ftw.journal.egg-info/dependency_links.txt
ftw.journal.egg-info/entry_points.txt
ftw.journal.egg-info/namespace_packages.txt
ftw.journal.egg-info/not-zip-safe
ftw.journal.egg-info/requires.txt
ftw.journal.egg-info/top_level.txt
ftw/journal/__init__.py
ftw/journal/config.py
ftw/journal/configure.zcml
ftw/journal/interfaces.py
ftw/journal/testing.py
ftw/journal/adapters/__init__.py
ftw/journal/adapters/annotations_journal.py
ftw/journal/adapters/configure.zcml
ftw/journal/adapters/workflow_history_journal.py
ftw/journal/events/__init__.py
ftw/journal/events/configure.zcml
ftw/journal/events/events.py
ftw/journal/events/handlers.py
ftw/journal/locales/ftw.journal.pot
ftw/journal/locales/plone.pot
ftw/journal/locales/de/LC_MESSAGES/ftw.journal.po
ftw/journal/locales/de/LC_MESSAGES/plone.po
ftw/journal/locales/fr/LC_MESSAGES/ftw.journal.po
ftw/journal/locales/fr/LC_MESSAGES/plone.po
ftw/journal/rules/__init__.py
ftw/journal/rules/configure.zcml
ftw/journal/rules/journal.py
ftw/journal/tests/__init__.py
ftw/journal/tests/test_integration.py
ftw/journal/tests/test_unit_adapters.py
ftw/journal/tests/test_unit_events.py
ftw/journal/tests/test_unit_interfaces.py