Metadata-Version: 2.1
Name: ftw.journal
Version: 1.4.0
Summary: Journaling infrastructure for plone
Home-page: https://github.com/4teamwork/ftw.journal
Author: 4teamwork AG
Author-email: mailto:info@4teamwork.ch
Maintainer: Jonas Baumann
License: GPL2
Keywords: plone workflow journal
Platform: UNKNOWN
Classifier: Framework :: Plone
Classifier: Framework :: Plone :: 4.3
Classifier: Framework :: Plone :: 5.1
Classifier: Programming Language :: Python
Classifier: Topic :: Software Development :: Libraries :: Python Modules
Provides-Extra: tests
